cognite/geospatial/__init__.py
cognite/geospatial/_client/__init__.py
cognite/geospatial/_client/api/__init__.py
cognite/geospatial/_client/api/spatial_api.py
cognite/geospatial/_client/api_client.py
cognite/geospatial/_client/configuration.py
cognite/geospatial/_client/exceptions.py
cognite/geospatial/_client/models/__init__.py
cognite/geospatial/_client/models/attribute_type_dto.py
cognite/geospatial/_client/models/core_geometry_spatial_item_all_of_dto.py
cognite/geospatial/_client/models/core_geometry_spatial_item_dto.py
cognite/geospatial/_client/models/core_spatial_item_dto.py
cognite/geospatial/_client/models/create_spatial_items_dto.py
cognite/geospatial/_client/models/crs_string_dto.py
cognite/geospatial/_client/models/cursor_dto.py
cognite/geospatial/_client/models/data_extractor_dto.py
cognite/geospatial/_client/models/either_id_dto.py
cognite/geospatial/_client/models/epoch_timestamp_range_dto.py
cognite/geospatial/_client/models/eps_code_dto.py
cognite/geospatial/_client/models/error_dto.py
cognite/geospatial/_client/models/external_id_dto.py
cognite/geospatial/_client/models/feature_attribute_dto.py
cognite/geospatial/_client/models/feature_layer_dto.py
cognite/geospatial/_client/models/feature_layer_name_dto.py
cognite/geospatial/_client/models/feature_layers_dto.py
cognite/geospatial/_client/models/feature_layers_filter_dto.py
cognite/geospatial/_client/models/file_spatial_info_dto.py
cognite/geospatial/_client/models/file_type_name_dto.py
cognite/geospatial/_client/models/full_spatial_item_all_of_dto.py
cognite/geospatial/_client/models/full_spatial_item_dto.py
cognite/geospatial/_client/models/full_spatial_items_dto.py
cognite/geospatial/_client/models/geo_json_dto.py
cognite/geospatial/_client/models/geometry_dto.py
cognite/geospatial/_client/models/geometry_items_dto.py
cognite/geospatial/_client/models/geometry_spatial_filter_dto.py
cognite/geospatial/_client/models/grid_coverage_item_dto.py
cognite_geospatial_sdk-0.10.4.dist-info/LICENSE
cognite_geospatial_sdk-0.10.4.dist-info/WHEEL
cognite_geospatial_sdk-0.10.4.dist-info/METADATA
cognite_geospatial_sdk-0.10.4.dist-info/RECORD
