Metadata-Version: 2.1
Name: cognite-geospatial-sdk
Version: 0.10.4
Summary: Cognite Geospatial SDK store and query spatial objects in 2D and 3D space
License: Apache-2.0
Keywords: geospatial,sdk,cognite
Author: Cognite AS
Author-email: support@cognite.com
Requires-Python: >=3.6,<4.0
Classifier: License :: OSI Approved :: Apache Software License
Classifier: Programming Language :: Python :: 3
Classifier: Programming Language :: Python :: 3.10
Classifier: Programming Language :: Python :: 3.6
Classifier: Programming Language :: Python :: 3.7
Classifier: Programming Language :: Python :: 3.8
Classifier: Programming Language :: Python :: 3.9
Requires-Dist: cognite-sdk-core (>=2.11.1,<3.0.0)
Requires-Dist: holoviews (>=1.13.4,<2.0.0)
Requires-Dist: numpy
Requires-Dist: pyarrow (>=3.0.0,<4.0.0)
Requires-Dist: python-dateutil (>=2.8,<3.0)
Requires-Dist: requests-oauthlib (>=1.3.0,<2.0.0)
Requires-Dist: scipy (>=1.5.4,<2.0.0)
Requires-Dist: shapely (>=1.7,<2.0)
Requires-Dist: six (>=1.15,<2.0)
Requires-Dist: urllib3 (>=1.25,<2.0)
Project-URL: Documentation, https://cognite-geospatial-sdk.readthedocs-hosted.com/en/latest/
